ngen_gitops/__init__.py
ngen_gitops/bitbucket.py
ngen_gitops/cli.py
ngen_gitops/config.py
ngen_gitops/git_wrapper.py
ngen_gitops/server.py
ngen_gitops/teams_notify.py
ngen_gitops-0.1.12.dist-info/METADATA
ngen_gitops-0.1.12.dist-info/WHEEL
ngen_gitops-0.1.12.dist-info/entry_points.txt
ngen_gitops-0.1.12.dist-info/top_level.txt
ngen_gitops-0.1.12.dist-info/RECORD
