Metadata-Version: 2.4
Name: ngen-gitops
Version: 0.1.12
Summary: GitOps CLI and web server for Bitbucket operations
Author: ngen-gitops contributors
License: MIT
Project-URL: Homepage, https://github.com/mamatnurahmat/ngen-gitops
Project-URL: Repository, https://github.com/mamatnurahmat/ngen-gitops
Project-URL: Issues, https://github.com/mamatnurahmat/ngen-gitops/issues
Keywords: cli,gitops,bitbucket,devops,api,ci-cd
Classifier: Development Status :: 3 - Alpha
Classifier: Intended Audience :: Developers
Classifier: Programming Language :: Python :: 3
Classifier: Programming Language :: Python :: 3.7
Classifier: Programming Language :: Python :: 3.8
Classifier: Programming Language :: Python :: 3.9
Classifier: Programming Language :: Python :: 3.10
Classifier: Programming Language :: Python :: 3.11
Requires-Python: >=3.7
Requires-Dist: requests>=2.25.0
Requires-Dist: fastapi>=0.68.0
Requires-Dist: uvicorn>=0.15.0
Requires-Dist: pyyaml>=5.4.0
Requires-Dist: python-dotenv>=0.19.0
